lionfuncs/__init__.py
lionfuncs/async_utils.py
lionfuncs/concurrency.py
lionfuncs/dict_utils.py
lionfuncs/errors.py
lionfuncs/format_utils.py
lionfuncs/hash_utils.py
lionfuncs/oai_schema_utils.py
lionfuncs/parsers.py
lionfuncs/py.typed
lionfuncs/to_dict.py
lionfuncs/to_json.py
lionfuncs/to_list.py
lionfuncs/utils.py
lionfuncs/file_system/__init__.py
lionfuncs/file_system/core.py
lionfuncs/file_system/media.py
lionfuncs/network/__init__.py
lionfuncs/network/adapters.py
lionfuncs/network/client.py
lionfuncs/network/endpoint.py
lionfuncs/network/events.py
lionfuncs/network/executor.py
lionfuncs/network/imodel.py
lionfuncs/network/primitives.py
lionfuncs/network/resilience.py
lionfuncs-3.2.0.dist-info/METADATA
lionfuncs-3.2.0.dist-info/WHEEL
lionfuncs-3.2.0.dist-info/licenses/LICENSE
lionfuncs-3.2.0.dist-info/RECORD
