Metadata-Version: 2.4
Name: lionfuncs
Version: 3.2.0
Summary: Hnady python functions
Author-email: HaiyangLi <quantocean.li@gmail.com>
License-File: LICENSE
Requires-Python: >=3.10
Requires-Dist: aiofiles>=23.0.0
Requires-Dist: anyio>=4.0
Requires-Dist: httpx>=0.27
Requires-Dist: pydantic>=2.0
Requires-Dist: rapidfuzz>=3.13.0
Requires-Dist: xmltodict>=0.14.2
Provides-Extra: all
Requires-Dist: anthropic>=0.5.0; extra == 'all'
Requires-Dist: dirtyjson>=1.0.8; extra == 'all'
Requires-Dist: openai>=1.0.0; extra == 'all'
Requires-Dist: pdf2image>=1.17; extra == 'all'
Provides-Extra: anthropic
Requires-Dist: anthropic>=0.5.0; extra == 'anthropic'
Provides-Extra: dirtyjson
Requires-Dist: dirtyjson>=1.0.8; extra == 'dirtyjson'
Provides-Extra: media
Requires-Dist: pdf2image>=1.17; extra == 'media'
Provides-Extra: openai
Requires-Dist: openai>=1.70.0; extra == 'openai'
